novella/__init__.py
novella/__main__.py
novella/action.py
novella/build.py
novella/compat.py
novella/graph.py
novella/markdown/flavor.py
novella/markdown/preprocessor.py
novella/markdown/tagparser.py
novella/markdown/tags/anchor.py
novella/markdown/tags/cat.py
novella/markdown/tags/shell.py
novella/novella.py
novella/py.typed
novella/repository.py
novella/template.py
novella/templates/hugo/__init__.py
novella/templates/hugo/installer.py
novella/templates/mkdocs.py
novella-0.2.6.dist-info/METADATA
novella-0.2.6.dist-info/WHEEL
novella-0.2.6.dist-info/entry_points.txt
novella-0.2.6.dist-info/RECORD
